{
    "version": "2.24.1",
    "architecture": {
        "32bit": {
            "url": "https://github.com/cli/cli/releases/download/v2.24.1/gh_2.24.1_windows_386.zip",
            "bin": [
                "bin/gh.exe"
            ],
            "hash": "39f45ab4cafbc9c616a38ff02141d8b6b75c9cbe2254eebdaab498b35b6db9fb"
        },
        "64bit": {
            "url": "https://github.com/cli/cli/releases/download/v2.24.1/gh_2.24.1_windows_amd64.zip",
            "bin": [
                "bin/gh.exe"
            ],
            "hash": "8fd4396621f1259da9a8421e0d539277fd3978f71798d65c67ed52256b79f3a5"
        }
    },
    "homepage": "https://github.com/cli/cli",
    "license": "MIT",
    "description": "GitHub CLI"
}
